classy_szfast/__init__.py
classy_szfast/classy_sz.py
classy_szfast/classy_szfast.py
classy_szfast/config.py
classy_szfast/cosmopower.py
classy_szfast/cosmopower_jax.py
classy_szfast/cosmosis_classy_szfast_interface.py
classy_szfast/emulators_meta_data.py
classy_szfast/pks_and_sigmas.py
classy_szfast/restore_nn.py
classy_szfast/suppress_warnings.py
classy_szfast/utils.py
classy_szfast/custom_bias/__init__.py
classy_szfast/custom_bias/custom_bias.py
classy_szfast/custom_profiles/__init__.py
classy_szfast/custom_profiles/custom_profiles.py
classy_szfast-0.0.25.post29.dist-info/METADATA
classy_szfast-0.0.25.post29.dist-info/WHEEL
classy_szfast-0.0.25.post29.dist-info/top_level.txt
classy_szfast-0.0.25.post29.dist-info/RECORD
