Metadata-Version: 2.4
Name: classy_szfast
Version: 0.0.25.post29
Summary: The accelerator of the class_sz code from https://github.com/CLASS-SZ
Maintainer-email: Boris Bolliet <bb667@cam.ac.uk>
License: MIT
Project-URL: Homepage, https://github.com/CLASS-SZ
Project-URL: GitHub, https://github.com/CLASS-SZ
Requires-Dist: numpy>=1.19.0
Requires-Dist: Cython>=0.29.21
Requires-Dist: tensorflow
Requires-Dist: mcfit>=0.0.22
Requires-Dist: get_cosmopower_emus>=0.0.15
Requires-Dist: class_sz_data>=0.0.13
Requires-Dist: cosmopower_jax==0.5.5
